textsummarizer_llm/__init__.py
textsummarizer_llm/main.py
textsummarizer_llm/prompts.py
textsummarizer_llm-2025.12.20201642.dist-info/METADATA
textsummarizer_llm-2025.12.20201642.dist-info/WHEEL
textsummarizer_llm-2025.12.20201642.dist-info/top_level.txt
textsummarizer_llm-2025.12.20201642.dist-info/RECORD
