Metadata-Version: 2.4
Name: textsummarizer-llm
Version: 2025.12.20201642
Summary: A new package that processes user-provided text inputs (such as headlines, descriptions, or extracted content from media) and returns structured, pattern-validated summaries using an LLM. It leverages
Author-email: textsummarizer-llm <hi@eugene.plus>
License: MIT
Project-URL: Homepage, https://github.com/chigwell/textsummarizer-llm
Requires-Python: >=3.9
Requires-Dist: langchain-llm7>=0.0.0
Requires-Dist: llmatch-messages>=0.0.0
Requires-Dist: langchain-core>=0.3.0
